paynesia/__init__.py
paynesia/contracts.py
paynesia/dto.py
paynesia/exceptions.py
paynesia/manager.py
paynesia/gateways/__init__.py
paynesia/gateways/ayoconnect.py
paynesia/gateways/doku.py
paynesia/gateways/duitku.py
paynesia/gateways/midtrans.py
paynesia/gateways/xendit.py
paynesia/services/__init__.py
paynesia/services/fonnte.py
paynesia-0.1.2.dist-info/licenses/LICENSE
paynesia-0.1.2.dist-info/METADATA
paynesia-0.1.2.dist-info/WHEEL
paynesia-0.1.2.dist-info/top_level.txt
paynesia-0.1.2.dist-info/RECORD
