Metadata-Version: 2.4
Name: paynesia
Version: 0.1.2
Summary: A framework-agnostic Python library for multiple payment gateways (Doku, Xendit, Midtrans, Duitku, AyoConnect) and Fonnte.
Author-email: Muhammad Fadhila Abiyyu Faris <fadhilaabiyyu@gmail.com>
License: MIT
Project-URL: Homepage, https://github.com/fadhila36/paynesia
Project-URL: Bug Tracker, https://github.com/fadhila36/paynesia/issues
Keywords: payment,gateway,midtrans,xendit,doku,duitku,ayoconnect,fonnte
Classifier: Development Status :: 3 - Alpha
Classifier: Intended Audience :: Developers
Classifier: Topic :: Software Development :: Libraries :: Python Modules
Classifier: License :: OSI Approved :: MIT License
Classifier: Programming Language :: Python :: 3
Requires-Python: >=3.7
License-File: LICENSE
Requires-Dist: requests
Dynamic: license-file
